{
  "$schema": "https://developer.microsoft.com/json-schemas/fabric/item/report/definition/visualContainer/2.4.0/schema.json",
  "name": "8f265ee4c04af8a3c519",
  "position": {
    "x": 380.16,
    "y": 24.137142857142859,
    "z": 4000,
    "height": 66.377142857142857,
    "width": 426.92571428571432,
    "tabOrder": 4000
  },
  "visual": {
    "visualType": "slicer",
    "query": {
      "queryState": {
        "Values": {
          "projections": [
            {
              "field": {
                "Column": {
                  "Expression": {
                    "SourceRef": {
                      "Entity": "primary_warehouses"
                    }
                  },
                  "Property": "warehouse_code"
                }
              },
              "queryRef": "primary_warehouses.warehouse_code",
              "nativeQueryRef": "warehouse_code",
              "active": true
            }
          ]
        }
      },
      "sortDefinition": {
        "isDefaultSort": true
      }
    },
    "objects": {
      "data": [
        {
          "properties": {
            "startDate": {
              "expr": {
                "Literal": {
                  "Value": "datetime'2024-08-01T00:00:00'"
                }
              }
            },
            "mode": {
              "expr": {
                "Literal": {
                  "Value": "'Basic'"
                }
              }
            }
          }
        }
      ],
      "slider": [
        {
          "properties": {
            "show": {
              "expr": {
                "Literal": {
                  "Value": "false"
                }
              }
            }
          }
        }
      ],
      "header": [
        {
          "properties": {
            "show": {
              "expr": {
                "Literal": {
                  "Value": "false"
                }
              }
            }
          }
        }
      ],
      "general": [
        {
          "properties": {
            "orientation": {
              "expr": {
                "Literal": {
                  "Value": "1D"
                }
              }
            },
            "outlineColor": {
              "solid": {
                "color": {
                  "expr": {
                    "ThemeDataColor": {
                      "ColorId": 2,
                      "Percent": 0
                    }
                  }
                }
              }
            },
            "filter": {
              "filter": {
                "Version": 2,
                "From": [
                  {
                    "Name": "p",
                    "Entity": "primary_warehouses",
                    "Type": 0
                  }
                ],
                "Where": [
                  {
                    "Condition": {
                      "In": {
                        "Expressions": [
                          {
                            "Column": {
                              "Expression": {
                                "SourceRef": {
                                  "Source": "p"
                                }
                              },
                              "Property": "warehouse_code"
                            }
                          }
                        ],
                        "Values": [
                          [
                            {
                              "Literal": {
                                "Value": "'MSO'"
                              }
                            }
                          ]
                        ]
                      }
                    }
                  }
                ]
              }
            }
          }
        }
      ],
      "selection": [
        {
          "properties": {
            "selectAllCheckboxEnabled": {
              "expr": {
                "Literal": {
                  "Value": "true"
                }
              }
            }
          }
        }
      ],
      "items": [
        {
          "properties": {
            "outlineStyle": {
              "expr": {
                "Literal": {
                  "Value": "2D"
                }
              }
            }
          }
        }
      ]
    },
    "visualContainerObjects": {
      "visualHeader": [
        {
          "properties": {
            "show": {
              "expr": {
                "Literal": {
                  "Value": "false"
                }
              }
            }
          }
        }
      ],
      "title": [
        {
          "properties": {
            "show": {
              "expr": {
                "Literal": {
                  "Value": "true"
                }
              }
            },
            "fontSize": {
              "expr": {
                "Literal": {
                  "Value": "12D"
                }
              }
            },
            "text": {
              "expr": {
                "Literal": {
                  "Value": "'Warehouse'"
                }
              }
            },
            "fontFamily": {
              "expr": {
                "Literal": {
                  "Value": "'''Segoe UI Light'', wf_segoe-ui_light, helvetica, arial, sans-serif'"
                }
              }
            }
          }
        }
      ],
      "border": [
        {
          "properties": {
            "show": {
              "expr": {
                "Literal": {
                  "Value": "true"
                }
              }
            },
            "radius": {
              "expr": {
                "Literal": {
                  "Value": "10D"
                }
              }
            },
            "color": {
              "solid": {
                "color": {
                  "expr": {
                    "ThemeDataColor": {
                      "ColorId": 2,
                      "Percent": 0
                    }
                  }
                }
              }
            }
          }
        }
      ],
      "divider": [
        {
          "properties": {
            "show": {
              "expr": {
                "Literal": {
                  "Value": "false"
                }
              }
            },
            "color": {
              "solid": {
                "color": {
                  "expr": {
                    "ThemeDataColor": {
                      "ColorId": 2,
                      "Percent": 0
                    }
                  }
                }
              }
            }
          }
        }
      ]
    },
    "drillFilterOtherVisuals": true
  },
  "filterConfig": {
    "filters": [
      {
        "name": "1ce47e2684eae16c68cc",
        "field": {
          "Column": {
            "Expression": {
              "SourceRef": {
                "Entity": "primary_warehouses"
              }
            },
            "Property": "warehouse_code"
          }
        },
        "type": "Categorical",
        "filter": {
          "Version": 2,
          "From": [
            {
              "Name": "p",
              "Entity": "primary_warehouses",
              "Type": 0
            }
          ],
          "Where": [
            {
              "Condition": {
                "Not": {
                  "Expression": {
                    "In": {
                      "Expressions": [
                        {
                          "Column": {
                            "Expression": {
                              "SourceRef": {
                                "Source": "p"
                              }
                            },
                            "Property": "warehouse_code"
                          }
                        }
                      ],
                      "Values": [
                        [
                          {
                            "Literal": {
                              "Value": "null"
                            }
                          }
                        ]
                      ]
                    }
                  }
                }
              }
            }
          ]
        },
        "objects": {
          "general": [
            {
              "properties": {
                "isInvertedSelectionMode": {
                  "expr": {
                    "Literal": {
                      "Value": "true"
                    }
                  }
                }
              }
            }
          ]
        }
      }
    ]
  }
}